verilog_stuff/count/counter.sv
`timescale 1ns/1ps

module counter (
    input  logic       clk,
    input  logic       reset,
    output logic [3:0] count
);

    always_ff @(posedge clk or posedge reset) begin
        if (reset) begin
            count <= 4'b0000;
        end else begin
            count <= count + 1'b1;
        end
    end

endmodule

verilog_stuff/count/tb_counter.sv
`timescale 1ns/1ps

module tb_counter;

    // inputs
    logic clk;
    logic reset;

    // outputs
    logic [3:0] count;

    counter uut (
        .clk(clk),
        .reset(reset),
        .count(count)
    );

    // clock (toggles every 5 time units = 10ns period)
    always #5 clk = ~clk;

    initial begin
        $dumpfile("waveform.vcd");
        $dumpvars(0, tb_counter);

        // initialise inputs
        clk = 0;
        reset = 1;

        #20;
        reset = 0;

        #200;

        $display("Simulation finished. Open waveform.vcd in GTKWave.");
        $finish;
    end

endmodule

verilog_stuff/count/waveform.vcd
$version Generated by VerilatedVcd $end
$timescale 1ps $end
 $scope module tb_counter $end
  $var wire 1 " clk $end
  $var wire 1 # reset $end
  $var wire 4 $ count [3:0] $end
  $scope module uut $end
   $var wire 1 " clk $end
   $var wire 1 # reset $end
   $var wire 4 $ count [3:0] $end
  $upscope $end
 $upscope $end
$enddefinitions $end


#0
0"
1#
b0000 $
#5000
1"
#10000
0"
#15000
1"
#20000
0"
0#
#25000
1"
b0001 $
#30000
0"
#35000
1"
b0010 $
#40000
0"
#45000
1"
b0011 $
#50000
0"
#55000
1"
b0100 $
#60000
0"
#65000
1"
b0101 $
#70000
0"
#75000
1"
b0110 $
#80000
0"
#85000
1"
b0111 $
#90000
0"
#95000
1"
b1000 $
#100000
0"
#105000
1"
b1001 $
#110000
0"
#115000
1"
b1010 $
#120000
0"
#125000
1"
b1011 $
#130000
0"
#135000
1"
b1100 $
#140000
0"
#145000
1"
b1101 $
#150000
0"
#155000
1"
b1110 $
#160000
0"
#165000
1"
b1111 $
#170000
0"
#175000
1"
b0000 $
#180000
0"
#185000
1"
b0001 $
#190000
0"
#195000
1"
b0010 $
#200000
0"
#205000
1"
b0011 $
#210000
0"
#215000
1"
b0100 $
